myst_libre/__init__.py
myst_libre/abstract_class.py
myst_libre/builders/__init__.py
myst_libre/builders/curvenote_builder.py
myst_libre/builders/myst_builder.py
myst_libre/rees/__init__.py
myst_libre/rees/rees.py
myst_libre/test/__init__.py
myst_libre/test/test_myst_libre.py
myst_libre/tools/__init__.py
myst_libre/tools/authenticator.py
myst_libre/tools/build_source_manager.py
myst_libre/tools/curvenote_client.py
myst_libre/tools/decorators.py
myst_libre/tools/docker_registry_client.py
myst_libre/tools/jupyter_hub_local_spawner.py
myst_libre/tools/myst_client.py
myst_libre/tools/rest_client.py
myst_libre-0.2.21.dist-info/licenses/LICENSE
myst_libre-0.2.21.dist-info/METADATA
myst_libre-0.2.21.dist-info/WHEEL
myst_libre-0.2.21.dist-info/top_level.txt
myst_libre-0.2.21.dist-info/RECORD
