Metadata-Version: 2.4
Name: myst_libre
Version: 0.2.21
Summary: A Python library for managing source code repositories, interacting with Docker registries, handling MyST markdown operations, and spawning JupyterHub instances locally.
Author-email: agahkarakuzu <agahkarakuzu@gmail.com>
License: MIT License
Project-URL: Homepage, https://github.com/neurolibre/myst_libre
Keywords: myst,docker,jupyterhub,markdown,repository
Classifier: Programming Language :: Python :: 3
Classifier: License :: OSI Approved :: MIT License
Classifier: Operating System :: OS Independent
Requires-Python: >=3.7
License-File: LICENSE
Requires-Dist: requests
Requires-Dist: docker
Requires-Dist: python-dotenv
Requires-Dist: PyGithub
Requires-Dist: termcolor
Requires-Dist: mystmd
Requires-Dist: repo2data
Requires-Dist: pyyaml
Dynamic: license-file
